Metadata-Version: 1.0
Name: scipion-empiar-depositor
Version: 1.0.0a3
Summary: A Scipion plugin to make depositions to EMPIAR
Home-page: https://github.com/yaizar/scipion_empiar_depositor
Author: Yaiza Rancel
Author-email: cyrancel@cnb.csic.es
License: UNKNOWN
Keywords: scipion empiar scipion-1.2
Platform: UNKNOWN
